tb/fifo_checker.sv
// ============================================================
// File: tb/fifo_checker.sv
// Description: Behavioral property checker — iverilog compatible
//              (Replaces SVA for iverilog environments)
// ============================================================

module fifo_checker #(
    parameter DATA_WIDTH = 8,
    parameter DEPTH      = 16
)(
    input logic                  clk,
    input logic                  rst_n,
    input logic                  wr_en,
    input logic                  rd_en,
    input logic [DATA_WIDTH-1:0] data_in,
    input logic [DATA_WIDTH-1:0] data_out,
    input logic                  full,
    input logic                  empty,
    input logic                  overflow,
    input logic                  underflow
);

    // Track previous rst_n to detect rising edge
    logic rst_n_prev;
    always @(posedge clk) rst_n_prev <= rst_n;

    // --------------------------------------------------------
    // CHECK 1: One cycle after reset release, FIFO must be empty
    // --------------------------------------------------------
    always @(posedge clk) begin
        if (rst_n_prev === 1'b0 && rst_n === 1'b1) begin
            // Wait one cycle to check empty
            @(posedge clk);
            if (empty !== 1'b1)
                $display("CHK FAIL [%0t]: CHECK 1 — empty should be 1 after reset", $time);
        end
    end

    // --------------------------------------------------------
    // CHECK 2: full and empty must never both be 1
    // --------------------------------------------------------
    always @(posedge clk) begin
        if (rst_n === 1'b1) begin
            if (full === 1'b1 && empty === 1'b1)
                $display("CHK FAIL [%0t]: CHECK 2 — full and empty both asserted simultaneously",
                          $time);
        end
    end

    // --------------------------------------------------------
    // CHECK 3: overflow must only occur when wr_en=1 AND full=1
    // --------------------------------------------------------
    always @(posedge clk) begin
        if (rst_n === 1'b1) begin
            if (overflow === 1'b1 && !(wr_en === 1'b1 && full === 1'b1))
                $display("CHK FAIL [%0t]: CHECK 3 — overflow asserted without wr_en && full",
                          $time);
        end
    end

    // --------------------------------------------------------
    // CHECK 4: underflow must only occur when rd_en=1 AND empty=1
    // --------------------------------------------------------
    always @(posedge clk) begin
        if (rst_n === 1'b1) begin
            if (underflow === 1'b1 && !(rd_en === 1'b1 && empty === 1'b1))
                $display("CHK FAIL [%0t]: CHECK 4 — underflow asserted without rd_en && empty",
                          $time);
        end
    end

    // --------------------------------------------------------
    // CHECK 5: writing when full must not reduce count
    //          (checked as: full stays high if only writing)
    // --------------------------------------------------------
    logic full_prev;
    always @(posedge clk) full_prev <= full;

    always @(posedge clk) begin
        if (rst_n === 1'b1) begin
            if (full_prev === 1'b1 && wr_en === 1'b1 && rd_en === 1'b0) begin
                if (full !== 1'b1)
                    $display("CHK FAIL [%0t]: CHECK 5 — full dropped on write-only when full",
                              $time);
            end
        end
    end

    // --------------------------------------------------------
    // CHECK 6: reading when empty must not change empty
    // --------------------------------------------------------
    logic empty_prev;
    always @(posedge clk) empty_prev <= empty;

    always @(posedge clk) begin
        if (rst_n === 1'b1) begin
            if (empty_prev === 1'b1 && rd_en === 1'b1 && wr_en === 1'b0) begin
                if (empty !== 1'b1)
                    $display("CHK FAIL [%0t]: CHECK 6 — empty dropped on read-only when empty",
                              $time);
            end
        end
    end

endmodule

rtl/sync_fifo.sv
// ============================================================
// File: rtl/sync_fifo.sv
// Description: Parameterized Synchronous FIFO
// Parameters:
//   DATA_WIDTH - width of each data word (default 8)
//   DEPTH      - number of entries in FIFO (default 16)
// ============================================================

module sync_fifo #(
    parameter DATA_WIDTH = 8,
    parameter DEPTH      = 16
)(
    input  logic                  clk,
    input  logic                  rst_n,
    input  logic                  wr_en,
    input  logic                  rd_en,
    input  logic [DATA_WIDTH-1:0] data_in,
    output logic [DATA_WIDTH-1:0] data_out,
    output logic                  full,
    output logic                  empty,
    output logic                  overflow,
    output logic                  underflow
);

    // --------------------------------------------------------
    // Internal signals
    // --------------------------------------------------------
    // DEPTH pointer bits need $clog2(DEPTH)+1 bits to detect wrap
    localparam PTR_WIDTH = $clog2(DEPTH);

    logic [DATA_WIDTH-1:0] mem [0:DEPTH-1];  // Memory array
    logic [PTR_WIDTH-1:0]  wr_ptr;           // Write pointer
    logic [PTR_WIDTH-1:0]  rd_ptr;           // Read pointer
    logic [PTR_WIDTH:0]    count;            // Number of valid entries

    // --------------------------------------------------------
    // Status flags
    // --------------------------------------------------------
    assign full  = (count == DEPTH);
    assign empty = (count == 0);

    // --------------------------------------------------------
    // Write logic
    // --------------------------------------------------------
    always_ff @(posedge clk) begin
        if (!rst_n) begin
            wr_ptr   <= '0;
            overflow <= 1'b0;
        end else begin
            overflow <= 1'b0;  // Default: clear overflow each cycle
            if (wr_en) begin
                if (!full) begin
                    mem[wr_ptr] <= data_in;
                    wr_ptr      <= (wr_ptr == DEPTH-1) ? '0 : wr_ptr + 1;
                end else begin
                    overflow    <= 1'b1;  // Write attempted when full
                end
            end
        end
    end

    // --------------------------------------------------------
    // Read logic
    // --------------------------------------------------------
    always_ff @(posedge clk) begin
        if (!rst_n) begin
            rd_ptr    <= '0;
            data_out  <= '0;
            underflow <= 1'b0;
        end else begin
            underflow <= 1'b0;  // Default: clear underflow each cycle
            if (rd_en) begin
                if (!empty) begin
                    data_out <= mem[rd_ptr];
                    rd_ptr   <= (rd_ptr == DEPTH-1) ? '0 : rd_ptr + 1;
                end else begin
                    underflow <= 1'b1;  // Read attempted when empty
                end
            end
        end
    end

    // --------------------------------------------------------
    // Count logic
    // wr_en valid = wr_en AND NOT full
    // rd_en valid = rd_en AND NOT empty
    // Simultaneous valid read and write = count stays same
    // --------------------------------------------------------
    always_ff @(posedge clk) begin
        if (!rst_n) begin
            count <= '0;
        end else begin
            case ({(wr_en && !full), (rd_en && !empty)})
                2'b10:   count <= count + 1;  // Write only
                2'b01:   count <= count - 1;  // Read only
                2'b11:   count <= count;      // Simultaneous read and write
                default: count <= count;      // No operation
            endcase
        end
    end

endmodule

tb/tb_top.sv
// ============================================================
// File: tb/tb_top.sv
// Description: Self-checking testbench for sync_fifo
// iverilog-compatible (no SVA, no inline variable declarations)
// ============================================================

`timescale 1ns/1ps

module tb_top;

    // --------------------------------------------------------
    // Parameters
    // --------------------------------------------------------
    localparam DATA_WIDTH = 8;
    localparam DEPTH      = 16;
    localparam CLK_PERIOD = 10;

    // --------------------------------------------------------
    // DUT signals
    // --------------------------------------------------------
    logic                  clk;
    logic                  rst_n;
    logic                  wr_en;
    logic                  rd_en;
    logic [DATA_WIDTH-1:0] data_in;
    logic [DATA_WIDTH-1:0] data_out;
    logic                  full;
    logic                  empty;
    logic                  overflow;
    logic                  underflow;

    // --------------------------------------------------------
    // All variables declared here — NOT inside begin blocks
    // This is required for iverilog compatibility
    // --------------------------------------------------------
    logic [DATA_WIDTH-1:0] ref_queue [$];    // Reference model queue
    logic [DATA_WIDTH-1:0] rd_expected;      // Expected read value
    integer                pass_count;
    integer                fail_count;
    integer                i;                // General loop variable
    integer                wr_val;           // Write value in loops

    // --------------------------------------------------------
    // DUT instantiation
    // --------------------------------------------------------
    sync_fifo #(
        .DATA_WIDTH(DATA_WIDTH),
        .DEPTH(DEPTH)
    ) dut (
        .clk       (clk),
        .rst_n     (rst_n),
        .wr_en     (wr_en),
        .rd_en     (rd_en),
        .data_in   (data_in),
        .data_out  (data_out),
        .full      (full),
        .empty     (empty),
        .overflow  (overflow),
        .underflow (underflow)
    );

    // --------------------------------------------------------
    // Plain-always checker (iverilog-safe replacement for SVA)
    // --------------------------------------------------------
    fifo_checker #(
        .DATA_WIDTH(DATA_WIDTH),
        .DEPTH(DEPTH)
    ) checker_inst (
        .clk       (clk),
        .rst_n     (rst_n),
        .wr_en     (wr_en),
        .rd_en     (rd_en),
        .data_in   (data_in),
        .data_out  (data_out),
        .full      (full),
        .empty     (empty),
        .overflow  (overflow),
        .underflow (underflow)
    );

    // --------------------------------------------------------
    // Clock
    // --------------------------------------------------------
    initial clk = 0;
    always #(CLK_PERIOD/2) clk = ~clk;

    // --------------------------------------------------------
    // VCD waveform dump
    // --------------------------------------------------------
    initial begin
        $dumpfile("sim/fifo_waves.vcd");
        $dumpvars(0, tb_top);
    end

    // --------------------------------------------------------
    // Task: reset_dut
    // --------------------------------------------------------
    task reset_dut;
        begin
            rst_n   = 1'b0;
            wr_en   = 1'b0;
            rd_en   = 1'b0;
            data_in = 8'h00;
            ref_queue = {};   // clear reference queue on reset
            repeat(4) @(posedge clk);
            #1;
            rst_n = 1'b1;
            @(posedge clk);
        end
    endtask

    // --------------------------------------------------------
    // Task: do_write
    // Drives wr_en for one cycle.
    // If write is accepted (not full), also pushes to ref queue.
    // --------------------------------------------------------
    task do_write;
        input [7:0] data;
        begin
            @(posedge clk); #1;
            wr_en   = 1'b1;
            data_in = data;
            @(posedge clk); #1;
            // Capture full BEFORE deasserting (full is sampled this cycle)
            if (!full) begin
                ref_queue.push_back(data);
            end
            wr_en = 1'b0;
        end
    endtask

    // --------------------------------------------------------
    // Task: checked_read
    // FIX v2: Two-phase read.
    //   Phase 1 — drive rd_en=1 for one clock
    //   Phase 2 — on the NEXT posedge, sample data_out
    //             (data_out is a registered output, 1-cycle latency)
    // --------------------------------------------------------
    task checked_read;
        begin
            @(posedge clk); #1;
            rd_en = 1'b1;
            @(posedge clk); #1;
            // data_out is now valid — sample it
            rd_en = 1'b0;

            if (ref_queue.size() > 0) begin
                rd_expected = ref_queue.pop_front();
                if (data_out === rd_expected) begin
                    $display("PASS: data_out=0x%02h  expected=0x%02h", data_out, rd_expected);
                    pass_count = pass_count + 1;
                end else begin
                    $display("FAIL: data_out=0x%02h  expected=0x%02h  *** MISMATCH ***",
                              data_out, rd_expected);
                    fail_count = fail_count + 1;
                end
            end else begin
                // queue empty — underflow expected
                if (underflow === 1'b1) begin
                    $display("PASS: underflow correctly asserted on empty read");
                    pass_count = pass_count + 1;
                end else begin
                    $display("FAIL: read on empty — underflow expected but not seen");
                    fail_count = fail_count + 1;
                end
            end
        end
    endtask

    // --------------------------------------------------------
    // Task: print_summary
    // --------------------------------------------------------
    task print_summary;
        begin
            $display("==============================================");
            $display("  FINAL RESULTS: %0d PASS  |  %0d FAIL",
                      pass_count, fail_count);
            if (fail_count == 0)
                $display("  STATUS: ALL TESTS PASSED");
            else
                $display("  STATUS: *** FAILURES — CHECK LOG ***");
            $display("==============================================");
        end
    endtask

    // --------------------------------------------------------
    // Timeout watchdog
    // --------------------------------------------------------
    initial begin
        #100000;
        $display("ERROR: Simulation timeout at %0t", $time);
        $finish;
    end

    // ============================================================
    // MAIN TEST SEQUENCE
    // ============================================================
    initial begin
        pass_count = 0;
        fail_count = 0;

        $display("==============================================");
        $display("  Sync FIFO Full Test Suite");
        $display("==============================================");

        // --------------------------------------------------
        // TEST 1: Reset
        // --------------------------------------------------
        $display("\n--- TEST 1: Reset ---");
        reset_dut();
        @(posedge clk); #1;
        if (empty === 1'b1 && full === 1'b0 &&
            overflow === 1'b0 && underflow === 1'b0) begin
            $display("PASS: Reset flags correct (empty=1 full=0 overflow=0 underflow=0)");
            pass_count = pass_count + 1;
        end else begin
            $display("FAIL: Reset flags wrong — empty=%b full=%b overflow=%b underflow=%b",
                      empty, full, overflow, underflow);
            fail_count = fail_count + 1;
        end

        // --------------------------------------------------
        // TEST 2: Basic write/read (order preservation)
        // --------------------------------------------------
        $display("\n--- TEST 2: Basic Write/Read ---");
        reset_dut();
        do_write(8'hAA);
        do_write(8'hBB);
        do_write(8'hCC);
        do_write(8'hDD);
        checked_read();  // expect AA
        checked_read();  // expect BB
        checked_read();  // expect CC
        checked_read();  // expect DD

        // --------------------------------------------------
        // TEST 3: Full condition
        // --------------------------------------------------
        $display("\n--- TEST 3: Full Condition ---");
        reset_dut();
        for (i = 0; i < DEPTH; i = i + 1) begin
            do_write(i[7:0]);
        end
        @(posedge clk); #1;
        if (full === 1'b1) begin
            $display("PASS: full=1 after %0d writes", DEPTH);
            pass_count = pass_count + 1;
        end else begin
            $display("FAIL: full=%b after %0d writes", full, DEPTH);
            fail_count = fail_count + 1;
        end

        // --------------------------------------------------
        // TEST 4: Empty condition
        // --------------------------------------------------
        $display("\n--- TEST 4: Empty Condition ---");
        reset_dut();
        do_write(8'h01);
        do_write(8'h02);
        do_write(8'h03);
        checked_read();
        checked_read();
        checked_read();
        @(posedge clk); #1;
        if (empty === 1'b1) begin
            $display("PASS: empty=1 after draining all entries");
            pass_count = pass_count + 1;
        end else begin
            $display("FAIL: empty=%b after draining", empty);
            fail_count = fail_count + 1;
        end

        // --------------------------------------------------
        // TEST 5: Overflow
        // --------------------------------------------------
        $display("\n--- TEST 5: Overflow ---");
        reset_dut();
        for (i = 0; i < DEPTH; i = i + 1) begin
            do_write(i[7:0]);
        end
        // Now write one more — must trigger overflow
        @(posedge clk); #1;
        wr_en   = 1'b1;
        data_in = 8'hFF;
        @(posedge clk); #1;
        wr_en = 1'b0;
        if (overflow === 1'b1) begin
            $display("PASS: overflow=1 on write when full");
            pass_count = pass_count + 1;
        end else begin
            $display("FAIL: overflow=%b — expected 1", overflow);
            fail_count = fail_count + 1;
        end

        // --------------------------------------------------
        // TEST 6: Underflow
        // --------------------------------------------------
        $display("\n--- TEST 6: Underflow ---");
        reset_dut();
        // Read from empty FIFO
        @(posedge clk); #1;
        rd_en = 1'b1;
        @(posedge clk); #1;
        rd_en = 1'b0;
        if (underflow === 1'b1) begin
            $display("PASS: underflow=1 on read when empty");
            pass_count = pass_count + 1;
        end else begin
            $display("FAIL: underflow=%b — expected 1", underflow);
            fail_count = fail_count + 1;
        end

        // --------------------------------------------------
        // TEST 7: Simultaneous read and write
        // --------------------------------------------------
        $display("\n--- TEST 7: Simultaneous Read/Write ---");
        reset_dut();
        do_write(8'h11);
        do_write(8'h22);
        do_write(8'h33);
        // Drive wr_en and rd_en in the same cycle
        @(posedge clk); #1;
        wr_en   = 1'b1;
        rd_en   = 1'b1;
        data_in = 8'h44;
        // Track: one read (pops 0x11), one write (pushes 0x44)
        rd_expected = ref_queue.pop_front(); // consume 0x11 from ref model
        ref_queue.push_back(8'h44);   // add 0x44 to ref model
        @(posedge clk); #1;
        wr_en = 1'b0;
        rd_en = 1'b0;
        // data_out should be 0x11 (sampled one cycle after rd_en)
        if (data_out === 8'h11) begin
            $display("PASS: Simultaneous R/W — data_out=0x11 correct");
            pass_count = pass_count + 1;
        end else begin
            $display("FAIL: Simultaneous R/W — data_out=0x%02h, expected=0x11", data_out);
            fail_count = fail_count + 1;
        end

        // --------------------------------------------------
        // TEST 8: Pointer wrap-around
        // --------------------------------------------------
        $display("\n--- TEST 8: Pointer Wrap-Around ---");
        reset_dut();
        // First fill and drain — advances pointers to wrap zone
        for (i = 0; i < DEPTH; i = i + 1) do_write(8'hA0 + i[7:0]);
        for (i = 0; i < DEPTH; i = i + 1) checked_read();
        // Second fill and drain — pointers must wrap correctly
        for (i = 0; i < DEPTH; i = i + 1) do_write(8'hB0 + i[7:0]);
        for (i = 0; i < DEPTH; i = i + 1) checked_read();
        @(posedge clk); #1;
        if (empty === 1'b1) begin
            $display("PASS: Wrap-around — FIFO empty after double fill/drain");
            pass_count = pass_count + 1;
        end else begin
            $display("FAIL: Wrap-around — empty=%b after double fill/drain", empty);
            fail_count = fail_count + 1;
        end

        // --------------------------------------------------
        // TEST 9: Random test (200 cycles)
        // FIX v2: ref_queue tracking happens BEFORE clock edge
        //         data_out sampled on the cycle AFTER rd_en
        // --------------------------------------------------
        $display("\n--- TEST 9: Random Test (200 cycles) ---");
        reset_dut();

        for (i = 0; i < 200; i = i + 1) begin
            // Generate pseudo-random stimulus
            wr_val  = ($urandom % 2);
            rd_en   = ($urandom % 2);
            wr_en   = wr_val[0];
            data_in = $urandom % 256;

            // Update reference model BEFORE clock edge
            // Write is accepted when wr_en=1 AND not full
            if (wr_en === 1'b1 && full === 1'b0)
                ref_queue.push_back(data_in);

            // Check for overflow (wr_en when full)
            if (wr_en === 1'b1 && full === 1'b1) begin
                // overflow will be checked on next clock
            end

            // Flag whether a valid read is expected this cycle
            // (rd_en=1 AND not empty AND queue has data)

            @(posedge clk); #1;

            // Now check results that landed on this posedge
            if (rd_en === 1'b1 && empty === 1'b0) begin
                // data_out is now updated — compare
                if (ref_queue.size() > 0) begin
                    rd_expected = ref_queue.pop_front();
                    if (data_out === rd_expected) begin
                        pass_count = pass_count + 1;
                    end else begin
                        $display("RAND FAIL [cycle %0d]: data_out=0x%02h expected=0x%02h",
                                  i, data_out, rd_expected);
                        fail_count = fail_count + 1;
                    end
                end
            end

            // Deassert for next iteration
            wr_en = 1'b0;
            rd_en = 1'b0;
        end
        $display("Random test complete.");

        // --------------------------------------------------
        // Final summary
        // --------------------------------------------------
        print_summary();
        #50;
        $finish;
    end

endmodule

sim/fifo_waves.vcd
$date
	Mon Mar 09 16:36:18 2026
$end
$version
	Icarus Verilog
$end
$timescale
	1ps
$end
$scope module tb_top $end
$var wire 1 ! underflow $end
$var wire 1 " overflow $end
$var wire 1 # full $end
$var wire 1 $ empty $end
$var wire 8 % data_out [7:0] $end
$var parameter 32 & CLK_PERIOD $end
$var parameter 32 ' DATA_WIDTH $end
$var parameter 32 ( DEPTH $end
$var reg 1 ) clk $end
$var reg 8 * data_in [7:0] $end
$var reg 1 + rd_en $end
$var reg 8 , rd_expected [7:0] $end
$var reg 1 - rst_n $end
$var reg 1 . wr_en $end
$var integer 32 / fail_count [31:0] $end
$var integer 32 0 i [31:0] $end
$var integer 32 1 pass_count [31:0] $end
$var integer 32 2 wr_val [31:0] $end
$scope module checker_inst $end
$var wire 1 ) clk $end
$var wire 8 3 data_in [7:0] $end
$var wire 1 + rd_en $end
$var wire 1 - rst_n $end
$var wire 1 . wr_en $end
$var wire 1 ! underflow $end
$var wire 1 " overflow $end
$var wire 1 # full $end
$var wire 1 $ empty $end
$var wire 8 4 data_out [7:0] $end
$var parameter 32 5 DATA_WIDTH $end
$var parameter 32 6 DEPTH $end
$var reg 1 7 empty_prev $end
$var reg 1 8 full_prev $end
$var reg 1 9 rst_n_prev $end
$upscope $end
$scope module dut $end
$var wire 1 ) clk $end
$var wire 8 : data_in [7:0] $end
$var wire 1 + rd_en $end
$var wire 1 - rst_n $end
$var wire 1 . wr_en $end
$var wire 1 # full $end
$var wire 1 $ empty $end
$var parameter 32 ; DATA_WIDTH $end
$var parameter 32 < DEPTH $end
$var parameter 32 = PTR_WIDTH $end
$var reg 5 > count [4:0] $end
$var reg 8 ? data_out [7:0] $end
$var reg 1 " overflow $end
$var reg 4 @ rd_ptr [3:0] $end
$var reg 1 ! underflow $end
$var reg 4 A wr_ptr [3:0] $end
$upscope $end
$scope task checked_read $end
$upscope $end
$scope task do_write $end
$var reg 8 B data [7:0] $end
$upscope $end
$scope task print_summary $end
$upscope $end
$scope task reset_dut $end
$upscope $end
$upscope $end
$enddefinitions $end
$comment Show the parameter values. $end
$dumpall
b100 =
b10000 <
b1000 ;
b10000 6
b1000 5
b10000 (
b1000 '
b1010 &
$end
#0
$dumpvars
bx B
bx A
bx @
bx ?
bx >
b0 :
x9
x8
x7
bx 4
b0 3
bx 2
b0 1
bx 0
b0 /
0.
0-
bx ,
0+
b0 *
0)
bx %
x$
x#
x"
x!
$end
#5000
0"
b0 A
0!
b0 %
b0 4
b0 ?
b0 @
0#
1$
b0 >
09
1)
#10000
0)
#15000
17
08
1)
#20000
0)
#25000
1)
#30000
0)
#35000
1)
#36000
1-
#40000
0)
#45000
19
1)
#50000
0)
#55000
1)
#56000
0-
b1 1
#60000
0)
#65000
09
1)
#70000
0)
#75000
1)
#80000
0)
#85000
1)
#90000
0)
#95000
1)
#96000
1-
#100000
0)
#105000
19
b10101010 B
1)
#110000
0)
#115000
1)
#116000
b10101010 *
b10101010 3
b10101010 :
1.
#120000
0)
#125000
b1 A
0$
b1 >
1)
#126000
b10111011 B
0.
#130000
0)
#135000
07
1)
#136000
b10111011 *
b10111011 3
b10111011 :
1.
#140000
0)
#145000
b10 A
b10 >
1)
#146000
b11001100 B
0.
#150000
0)
#155000
1)
#156000
b11001100 *
b11001100 3
b11001100 :
1.
#160000
0)
#165000
b11 A
b11 >
1)
#166000
b11011101 B
0.
#170000
0)
#175000
1)
#176000
b11011101 *
b11011101 3
b11011101 :
1.
#180000
0)
#185000
b100 A
b100 >
1)
#186000
0.
#190000
0)
#195000
1)
#196000
1+
#200000
0)
#205000
b1 @
b10101010 %
b10101010 4
b10101010 ?
b11 >
1)
#206000
b10 1
b10101010 ,
0+
#210000
0)
#215000
1)
#216000
1+
#220000
0)
#225000
b10 @
b10111011 %
b10111011 4
b10111011 ?
b10 >
1)
#226000
b11 1
b10111011 ,
0+
#230000
0)
#235000
1)
#236000
1+
#240000
0)
#245000
b11 @
b11001100 %
b11001100 4
b11001100 ?
b1 >
1)
#246000
b100 1
b11001100 ,
0+
#250000
0)
#255000
1)
#256000
1+
#260000
0)
#265000
b100 @
b11011101 %
b11011101 4
b11011101 ?
1$
b0 >
1)
#266000
b0 *
b0 3
b0 :
0-
b101 1
b11011101 ,
0+
#270000
0)
#275000
17
09
b0 %
b0 4
b0 ?
b0 @
b0 A
1)
#280000
0)
#285000
1)
#290000
0)
#295000
1)
#300000
0)
#305000
1)
#306000
1-
#310000
0)
#315000
19
b0 B
b0 0
1)
#320000
0)
#325000
1)
#326000
1.
#330000
0)
#335000
0$
b1 >
b1 A
1)
#336000
b1 B
b1 0
0.
#340000
0)
#345000
07
1)
#346000
b1 *
b1 3
b1 :
1.
#350000
0)
#355000
b10 >
b10 A
1)
#356000
b10 B
b10 0
0.
#360000
0)
#365000
1)
#366000
b10 *
b10 3
b10 :
1.
#370000
0)
#375000
b11 >
b11 A
1)
#376000
b11 B
b11 0
0.
#380000
0)
#385000
1)
#386000
b11 *
b11 3
b11 :
1.
#390000
0)
#395000
b100 >
b100 A
1)
#396000
b100 B
b100 0
0.
#400000
0)
#405000
1)
#406000
b100 *
b100 3
b100 :
1.
#410000
0)
#415000
b101 >
b101 A
1)
#416000
b101 B
b101 0
0.
#420000
0)
#425000
1)
#426000
b101 *
b101 3
b101 :
1.
#430000
0)
#435000
b110 >
b110 A
1)
#436000
b110 B
b110 0
0.
#440000
0)
#445000
1)
#446000
b110 *
b110 3
b110 :
1.
#450000
0)
#455000
b111 >
b111 A
1)
#456000
b111 B
b111 0
0.
#460000
0)
#465000
1)
#466000
b111 *
b111 3
b111 :
1.
#470000
0)
#475000
b1000 >
b1000 A
1)
#476000
b1000 B
b1000 0
0.
#480000
0)
#485000
1)
#486000
b1000 *
b1000 3
b1000 :
1.
#490000
0)
#495000
b1001 >
b1001 A
1)
#496000
b1001 B
b1001 0
0.
#500000
0)
#505000
1)
#506000
b1001 *
b1001 3
b1001 :
1.
#510000
0)
#515000
b1010 >
b1010 A
1)
#516000
b1010 B
b1010 0
0.
#520000
0)
#525000
1)
#526000
b1010 *
b1010 3
b1010 :
1.
#530000
0)
#535000
b1011 >
b1011 A
1)
#536000
b1011 B
b1011 0
0.
#540000
0)
#545000
1)
#546000
b1011 *
b1011 3
b1011 :
1.
#550000
0)
#555000
b1100 >
b1100 A
1)
#556000
b1100 B
b1100 0
0.
#560000
0)
#565000
1)
#566000
b1100 *
b1100 3
b1100 :
1.
#570000
0)
#575000
b1101 >
b1101 A
1)
#576000
b1101 B
b1101 0
0.
#580000
0)
#585000
1)
#586000
b1101 *
b1101 3
b1101 :
1.
#590000
0)
#595000
b1110 >
b1110 A
1)
#596000
b1110 B
b1110 0
0.
#600000
0)
#605000
1)
#606000
b1110 *
b1110 3
b1110 :
1.
#610000
0)
#615000
b1111 >
b1111 A
1)
#616000
b1111 B
b1111 0
0.
#620000
0)
#625000
1)
#626000
b1111 *
b1111 3
b1111 :
1.
#630000
0)
#635000
1#
b10000 >
b0 A
1)
#636000
b10000 0
0.
#640000
0)
#645000
18
1)
#646000
b0 *
b0 3
b0 :
0-
b110 1
#650000
0)
#655000
09
0#
1$
b0 >
1)
#660000
0)
#665000
08
17
1)
#670000
0)
#675000
1)
#680000
0)
#685000
1)
#686000
1-
#690000
0)
#695000
19
b1 B
1)
#700000
0)
#705000
1)
#706000
b1 *
b1 3
b1 :
1.
#710000
0)
#715000
0$
b1 >
b1 A
1)
#716000
b10 B
0.
#720000
0)
#725000
07
1)
#726000
b10 *
b10 3
b10 :
1.
#730000
0)
#735000
b10 >
b10 A
1)
#736000
b11 B
0.
#740000
0)
#745000
1)
#746000
b11 *
b11 3
b11 :
1.
#750000
0)
#755000
b11 >
b11 A
1)
#756000
0.
#760000
0)
#765000
1)
#766000
1+
#770000
0)
#775000
b10 >
b1 @
b1 %
b1 4
b1 ?
1)
#776000
b111 1
b1 ,
0+
#780000
0)
#785000
1)
#786000
1+
#790000
0)
#795000
b1 >
b10 @
b10 %
b10 4
b10 ?
1)
#796000
b1000 1
b10 ,
0+
#800000
0)
#805000
1)
#806000
1+
#810000
0)
#815000
1$
b0 >
b11 @
b11 %
b11 4
b11 ?
1)
#816000
b1001 1
b11 ,
0+
#820000
0)
#825000
17
1)
#826000
b0 *
b0 3
b0 :
0-
b1010 1
#830000
0)
#835000
09
b0 %
b0 4
b0 ?
b0 @
b0 A
1)
#840000
0)
#845000
1)
#850000
0)
#855000
1)
#860000
0)
#865000
1)
#866000
1-
#870000
0)
#875000
19
b0 B
b0 0
1)
#880000
0)
#885000
1)
#886000
1.
#890000
0)
#895000
0$
b1 >
b1 A
1)
#896000
b1 B
b1 0
0.
#900000
0)
#905000
07
1)
#906000
b1 *
b1 3
b1 :
1.
#910000
0)
#915000
b10 >
b10 A
1)
#916000
b10 B
b10 0
0.
#920000
0)
#925000
1)
#926000
b10 *
b10 3
b10 :
1.
#930000
0)
#935000
b11 >
b11 A
1)
#936000
b11 B
b11 0
0.
#940000
0)
#945000
1)
#946000
b11 *
b11 3
b11 :
1.
#950000
0)
#955000
b100 >
b100 A
1)
#956000
b100 B
b100 0
0.
#960000
0)
#965000
1)
#966000
b100 *
b100 3
b100 :
1.
#970000
0)
#975000
b101 >
b101 A
1)
#976000
b101 B
b101 0
0.
#980000
0)
#985000
1)
#986000
b101 *
b101 3
b101 :
1.
#990000
0)
#995000
b110 >
b110 A
1)
#996000
b110 B
b110 0
0.
#1000000
0)
#1005000
1)
#1006000
b110 *
b110 3
b110 :
1.
#1010000
0)
#1015000
b111 >
b111 A
1)
#1016000
b111 B
b111 0
0.
#1020000
0)
#1025000
1)
#1026000
b111 *
b111 3
b111 :
1.
#1030000
0)
#1035000
b1000 >
b1000 A
1)
#1036000
b1000 B
b1000 0
0.
#1040000
0)
#1045000
1)
#1046000
b1000 *
b1000 3
b1000 :
1.
#1050000
0)
#1055000
b1001 >
b1001 A
1)
#1056000
b1001 B
b1001 0
0.
#1060000
0)
#1065000
1)
#1066000
b1001 *
b1001 3
b1001 :
1.
#1070000
0)
#1075000
b1010 >
b1010 A
1)
#1076000
b1010 B
b1010 0
0.
#1080000
0)
#1085000
1)
#1086000
b1010 *
b1010 3
b1010 :
1.
#1090000
0)
#1095000
b1011 >
b1011 A
1)
#1096000
b1011 B
b1011 0
0.
#1100000
0)
#1105000
1)
#1106000
b1011 *
b1011 3
b1011 :
1.
#1110000
0)
#1115000
b1100 >
b1100 A
1)
#1116000
b1100 B
b1100 0
0.
#1120000
0)
#1125000
1)
#1126000
b1100 *
b1100 3
b1100 :
1.
#1130000
0)
#1135000
b1101 >
b1101 A
1)
#1136000
b1101 B
b1101 0
0.
#1140000
0)
#1145000
1)
#1146000
b1101 *
b1101 3
b1101 :
1.
#1150000
0)
#1155000
b1110 >
b1110 A
1)
#1156000
b1110 B
b1110 0
0.
#1160000
0)
#1165000
1)
#1166000
b1110 *
b1110 3
b1110 :
1.
#1170000
0)
#1175000
b1111 >
b1111 A
1)
#1176000
b1111 B
b1111 0
0.
#1180000
0)
#1185000
1)
#1186000
b1111 *
b1111 3
b1111 :
1.
#1190000
0)
#1195000
1#
b10000 >
b0 A
1)
#1196000
b10000 0
0.
#1200000
0)
#1205000
18
1)
#1206000
b11111111 *
b11111111 3
b11111111 :
1.
#1210000
0)
#1215000
1"
1)
#1216000
b0 *
b0 3
b0 :
0-
b1011 1
0.
#1220000
0)
#1225000
0"
0#
1$
b0 >
09
1)
#1230000
0)
#1235000
17
08
1)
#1240000
0)
#1245000
1)
#1250000
0)
#1255000
1)
#1256000
1-
#1260000
0)
#1265000
19
1)
#1270000
0)
#1275000
1)
#1276000
1+
#1280000
0)
#1285000
1!
1)
#1286000
0-
b1100 1
0+
#1290000
0)
#1295000
09
0!
1)
#1300000
0)
#1305000
1)
#1310000
0)
#1315000
1)
#1320000
0)
#1325000
1)
#1326000
1-
#1330000
0)
#1335000
19
b10001 B
1)
#1340000
0)
#1345000
1)
#1346000
b10001 *
b10001 3
b10001 :
1.
#1350000
0)
#1355000
0$
b1 >
b1 A
1)
#1356000
b100010 B
0.
#1360000
0)
#1365000
07
1)
#1366000
b100010 *
b100010 3
b100010 :
1.
#1370000
0)
#1375000
b10 >
b10 A
1)
#1376000
b110011 B
0.
#1380000
0)
#1385000
1)
#1386000
b110011 *
b110011 3
b110011 :
1.
#1390000
0)
#1395000
b11 >
b11 A
1)
#1396000
0.
#1400000
0)
#1405000
1)
#1406000
b10001 ,
b1000100 *
b1000100 3
b1000100 :
1+
1.
#1410000
0)
#1415000
b1 @
b10001 %
b10001 4
b10001 ?
b100 A
1)
#1416000
b0 *
b0 3
b0 :
0-
b1101 1
0+
0.
#1420000
0)
#1425000
b0 A
b0 %
b0 4
b0 ?
b0 @
1$
b0 >
09
1)
#1430000
0)
#1435000
17
1)
#1440000
0)
#1445000
1)
#1450000
0)
#1455000
1)
#1456000
1-
#1460000
0)
#1465000
19
b10100000 B
b0 0
1)
#1470000
0)
#1475000
1)
#1476000
b10100000 *
b10100000 3
b10100000 :
1.
#1480000
0)
#1485000
b1 A
0$
b1 >
1)
#1486000
b10100001 B
b1 0
0.
#1490000
0)
#1495000
07
1)
#1496000
b10100001 *
b10100001 3
b10100001 :
1.
#1500000
0)
#1505000
b10 A
b10 >
1)
